sinapsis_retina_face_trt/__init__.py
sinapsis_retina_face_trt/helpers/__init__.py
sinapsis_retina_face_trt/helpers/tags.py
sinapsis_retina_face_trt/templates/__init__.py
sinapsis_retina_face_trt/templates/retina_face/__init__.py
sinapsis_retina_face_trt/templates/retina_face/deepface_face_recognition.py
sinapsis_retina_face_trt/templates/retina_face/deepface_face_recognition_dev.py
sinapsis_retina_face_trt/templates/retina_face/face_verification_from_gallery.py
sinapsis_retina_face_trt/templates/retina_face/pytorch_embedding_search_from_gallery.py
sinapsis_retina_face_trt/templates/retina_face/retina_face_pytorch.py
sinapsis_retina_face_trt/templates/retina_face/retina_face_pytorch_trt.py
sinapsis_retina_face_trt/templates/retina_face/model_converters/__init__.py
sinapsis_retina_face_trt/templates/retina_face/model_converters/face_net_converter.py
sinapsis_retina_face_trt-0.1.14.dist-info/licenses/LICENSE
sinapsis_retina_face_trt-0.1.14.dist-info/METADATA
sinapsis_retina_face_trt-0.1.14.dist-info/WHEEL
sinapsis_retina_face_trt-0.1.14.dist-info/top_level.txt
sinapsis_retina_face_trt-0.1.14.dist-info/RECORD
