Metadata-Version: 2.4
Name: sinapsis-retina-face-trt
Version: 0.1.14
Summary: trt version of retina face and facenet
Author-email: SinapsisAI <dev@sinapsis.tech>
Project-URL: Homepage, https://sinapsis.tech
Project-URL: Documentation, https://docs.sinapsis.tech/docs
Project-URL: Tutorials, https://docs.sinapsis.tech/tutorials
Project-URL: Repository, https://github.com/Sinapsis-AI/sinapsis-retina-face-trt.git
Requires-Python: >=3.10
License-File: LICENSE
Requires-Dist: packaging>=24.2
Requires-Dist: polars>=1.26.0
Requires-Dist: retinaface-pytorch>=0.0.7
Requires-Dist: sinapsis>=0.2.3
Requires-Dist: sinapsis-data-readers>=0.1.2
Provides-Extra: model-conversion
Requires-Dist: deepface==0.0.92; extra == "model-conversion"
Requires-Dist: sinapsis-framework-converter[all]>=0.1.8; extra == "model-conversion"
Provides-Extra: webapp-gradio
Requires-Dist: sinapsis-retina-face-trt[sinapsis-data-visualization]; extra == "webapp-gradio"
Requires-Dist: sinapsis[webapp]>=0.2.3; extra == "webapp-gradio"
Provides-Extra: sinapsis-data-visualization
Requires-Dist: sinapsis-data-visualization[visualization-matplotlib]>=0.1.0; extra == "sinapsis-data-visualization"
Provides-Extra: sinapsis-data-writers
Requires-Dist: sinapsis-data-writers>=0.1.1; extra == "sinapsis-data-writers"
Provides-Extra: all
Requires-Dist: sinapsis-retina-face-trt[dev,model-conversion,sinapsis-data-visualization,sinapsis-data-writers,webapp-gradio]; extra == "all"
Dynamic: license-file
